terrarium_assembler/__init__.py
terrarium_assembler/cli.py
terrarium_assembler/nuitkaflags.py
terrarium_assembler/nuitkaprofiles.py
terrarium_assembler/ta.py
terrarium_assembler/utils.py
terrarium_assembler-1.3.1.dist-info/LICENSE
terrarium_assembler-1.3.1.dist-info/METADATA
terrarium_assembler-1.3.1.dist-info/WHEEL
terrarium_assembler-1.3.1.dist-info/entry_points.txt
terrarium_assembler-1.3.1.dist-info/top_level.txt
terrarium_assembler-1.3.1.dist-info/RECORD
