Metadata-Version: 2.1
Name: terrarium-assembler
Version: 1.3.1
Summary: Generate Portable Linux Applications, just portable folders
Home-page: https://github.com/belonesox/terrarium_assembler
Author: Stas Fomin
Author-email: stas-fomin@yandex.ru
License: MIT license
Keywords: terrarium_assembler
Platform: UNKNOWN
Classifier: Development Status :: 2 - Pre-Alpha
Classifier: Intended Audience :: Developers
Classifier: License :: OSI Approved :: MIT License
Classifier: Natural Language :: English
Classifier: Programming Language :: Python :: 3
Classifier: Programming Language :: Python :: 3.7
Classifier: Programming Language :: Python :: 3.8
Requires-Python: >=3.7
License-File: LICENSE
Requires-Dist: easydict
Requires-Dist: pytictoc
Requires-Dist: file-magic
Requires-Dist: python-magic
Requires-Dist: jinja2
Requires-Dist: pyyaml
Requires-Dist: prettytable
Requires-Dist: pipenv
Requires-Dist: wheel-filename
